physio_cassette/__init__.py
physio_cassette/physio_cassette.py
physio_cassette-0.2.15.dist-info/licenses/LICENSE
physio_cassette-0.2.15.dist-info/METADATA
physio_cassette-0.2.15.dist-info/WHEEL
physio_cassette-0.2.15.dist-info/top_level.txt
physio_cassette-0.2.15.dist-info/RECORD
