Metadata-Version: 2.4
Name: physio_cassette
Version: 0.2.15
Summary: Storage structures for signals (mostly physiological data), metadata and event annotations
Project-URL: homepage, https://codeberg.org/LucaCerina/physio-cassette
Project-URL: Bug Tracker, https://codeberg.org/LucaCerina/physio-cassette/issues
Keywords: data storage,physiological signals,event records
Classifier: Programming Language :: Python :: 3
Classifier: License :: OSI Approved :: MIT License
Classifier: Operating System :: OS Independent
Classifier: Development Status :: 4 - Beta
Requires-Python: >=3.11
License-File: LICENSE
Requires-Dist: numpy>2.0
Requires-Dist: openpyxl<=3.1
Requires-Dist: openpyxl-dictreader>=0.1.9
Requires-Dist: xlrd>=2.0.2
Requires-Dist: pyedflib>=0.1.40
Requires-Dist: pymatreader>=1.0.0
Requires-Dist: python-dateutil>=2.9.0
Requires-Dist: scipy>=1.16
Requires-Dist: traces>=0.5.1
Requires-Dist: wfdb>=4.3.0
Requires-Dist: xmltodict>=0.13.0
Dynamic: license-file
